{"Mar 2014": {"Equity Capital": "8245", "Reserves": "77570", "Borrowings": "67170", "Long term Borrowings": "62406", "Short term Borrowings": "0", "Lease Liabilities": "0", "Other Borrowings": "4764", "Other Liabilities": "26641", "Trade Payables": "6430", "Advance from Customers": "383", "Other liability items": "19828", "Total Liabilities": "179627", "Fixed Assets": "72111", "Land": "8152", "Building": "8171", "Plant Machinery": "95211", "Equipments": "337", "Computers": "400", "Furniture n fittings": "884", "Railway sidings": "594", "Vehicles": "12", "Intangible Assets": "0", "Other fixed assets": "3232", "Gross Block": "116992", "Accumulated Depreciation": "44881", "CWIP": "44889", "Investments": "9758", "Other Assets": "52869", "Inventories": "5446", "Trade receivables": "5220", "Cash Equivalents": "15311", "Loans n Advances": "1929", "Other asset items": "24963", "Total Assets": "179627"}, "Mar 2015": {"Equity Capital": "8245", "Reserves": "73412", "Borrowings": "85995", "Long term Borrowings": "78532", "Short term Borrowings": "0", "Lease Liabilities": "0", "Other Borrowings": "7463", "Other Liabilities": "29568", "Trade Payables": "5953", "Advance from Customers": "462", "Other liability items": "23153", "Total Liabilities": "197220", "Fixed Assets": "78849", "Land": "9689", "Building": "9123", "Plant Machinery": "103597", "Equipments": "567", "Computers": "423", "Furniture n fittings": "972", "Railway sidings": "751", "Vehicles": "13", "Intangible Assets": "0", "Other fixed assets": "3343", "Gross Block": "128478", "Accumulated Depreciation": "49629", "CWIP": "56493", "Investments": "9032", "Other Assets": "52846", "Inventories": "7539", "Trade receivables": "7604", "Cash Equivalents": "12879", "Loans n Advances": "1166", "Other asset items": "23657", "Total Assets": "197220"}, "Mar 2016": {"Equity Capital": "8245", "Reserves": "83048", "Borrowings": "93127", "Long term Borrowings": "85097", "Short term Borrowings": "1300", "Lease Liabilities": "0", "Other Borrowings": "6731", "Other Liabilities": "30810", "Trade Payables": "5312", "Advance from Customers": "1241", "Other liability items": "24258", "Total Liabilities": "215231", "Fixed Assets": "91773", "Land": "11245", "Building": "7113", "Plant Machinery": "70828", "Equipments": "371", "Computers": "142", "Furniture n fittings": "622", "Railway sidings": "650", "Vehicles": "10", "Intangible Assets": "0", "Other fixed assets": "6646", "Gross Block": "97625", "Accumulated Depreciation": "5852", "CWIP": "66423", "Investments": "8393", "Other Assets": "48642", "Inventories": "7103", "Trade receivables": "7732", "Cash Equivalents": "4461", "Loans n Advances": "1472", "Other asset items": "27873", "Total Assets": "215231"}, "Mar 2017": {"Equity Capital": "8245", "Reserves": "87986", "Borrowings": "106840", "Long term Borrowings": "97339", "Short term Borrowings": "3001", "Lease Liabilities": "0", "Other Borrowings": "6500", "Other Liabilities": "33609", "Trade Payables": "4876", "Advance from Customers": "690", "Other liability items": "28043", "Total Liabilities": "236680", "Fixed Assets": "99356", "Land": "11923", "Building": "7872", "Plant Machinery": "82749", "Equipments": "451", "Computers": "273", "Furniture n fittings": "774", "Railway sidings": "758", "Vehicles": "14", "Intangible Assets": "204", "Other fixed assets": "6733", "Gross Block": "111750", "Accumulated Depreciation": "12394", "CWIP": "80737", "Investments": "8248", "Other Assets": "48339", "Inventories": "6608", "Trade receivables": "8138", "Cash Equivalents": "2930", "Loans n Advances": "1452", "Other asset items": "29211", "Total Assets": "236680"}, "Mar 2018": {"Equity Capital": "8245", "Reserves": "93532", "Borrowings": "121605", "Long term Borrowings": "108698", "Short term Borrowings": "6500", "Lease Liabilities": "0", "Other Borrowings": "6407", "Other Liabilities": "44579", "Trade Payables": "5593", "Advance from Customers": "454", "Other liability items": "38532", "Total Liabilities": "267962", "Fixed Assets": "119759", "Land": "10762", "Building": "9804", "Plant Machinery": "108445", "Equipments": "580", "Computers": "319", "Furniture n fittings": "1015", "Railway sidings": "1461", "Vehicles": "15", "Intangible Assets": "204", "Other fixed assets": "7201", "Gross Block": "139805", "Accumulated Depreciation": "20046", "CWIP": "79076", "Investments": "10047", "Other Assets": "59079", "Inventories": "6187", "Trade receivables": "7578", "Cash Equivalents": "3978", "Loans n Advances": "7578", "Other asset items": "33757", "Total Assets": "267962"}, "Mar 2019": {"Equity Capital": "9895", "Reserves": "97514", "Borrowings": "142807", "Long term Borrowings": "119698", "Short term Borrowings": "15376", "Lease Liabilities": "0", "Other Borrowings": "7732", "Other Liabilities": "40787", "Trade Payables": "7551", "Advance from Customers": "183", "Other liability items": "33053", "Total Liabilities": "291002", "Fixed Assets": "125621", "Land": "11438", "Building": "10905", "Plant Machinery": "119541", "Equipments": "675", "Computers": "397", "Furniture n fittings": "1218", "Railway sidings": "1652", "Vehicles": "16", "Intangible Assets": "204", "Other fixed assets": "7354", "Gross Block": "153399", "Accumulated Depreciation": "27779", "CWIP": "91207", "Investments": "13146", "Other Assets": "61029", "Inventories": "8239", "Trade receivables": "8434", "Cash Equivalents": "2144", "Loans n Advances": "9836", "Other asset items": "32375", "Total Assets": "291002"}, "Mar 2020": {"Equity Capital": "9895", "Reserves": "103675", "Borrowings": "168712", "Long term Borrowings": "146539", "Short term Borrowings": "14049", "Lease Liabilities": "0", "Other Borrowings": "8124", "Other Liabilities": "45557", "Trade Payables": "9001", "Advance from Customers": "612", "Other liability items": "35944", "Total Liabilities": "327838", "Fixed Assets": "156811", "Land": "8990", "Building": "13875", "Plant Machinery": "150630", "Equipments": "836", "Computers": "398", "Furniture n fittings": "2315", "Railway sidings": "3191", "Vehicles": "39", "Intangible Assets": "385", "Other fixed assets": "12917", "Gross Block": "193575", "Accumulated Depreciation": "36764", "CWIP": "73359", "Investments": "26401", "Other Assets": "71266", "Inventories": "10902", "Trade receivables": "15615", "Cash Equivalents": "2209", "Loans n Advances": "2248", "Other asset items": "40292", "Total Assets": "327838"}, "Mar 2021": {"Equity Capital": "9697", "Reserves": "109289", "Borrowings": "176466", "Long term Borrowings": "150509", "Short term Borrowings": "23107", "Lease Liabilities": "872", "Other Borrowings": "1978", "Other Liabilities": "47915", "Trade Payables": "7182", "Advance from Customers": "536", "Other liability items": "40196", "Total Liabilities": "343367", "Fixed Assets": "164449", "Land": "6430", "Building": "14673", "Plant Machinery": "165450", "Equipments": "927", "Computers": "459", "Furniture n fittings": "2532", "Railway sidings": "3295", "Vehicles": "40", "Intangible Assets": "420", "Other fixed assets": "18078", "Gross Block": "212304", "Accumulated Depreciation": "47856", "CWIP": "75438", "Investments": "28626", "Other Assets": "74854", "Inventories": "9369", "Trade receivables": "22976", "Cash Equivalents": "2338", "Loans n Advances": "3742", "Other asset items": "36429", "Total Assets": "343367"}, "Mar 2022": {"Equity Capital": "9697", "Reserves": "118971", "Borrowings": "185578", "Long term Borrowings": "160122", "Short term Borrowings": "24472", "Lease Liabilities": "983", "Other Borrowings": "0", "Other Liabilities": "57115", "Trade Payables": "9734", "Advance from Customers": "437", "Other liability items": "46944", "Total Liabilities": "371361", "Fixed Assets": "195571", "Land": "10538", "Building": "16890", "Plant Machinery": "204482", "Equipments": "1043", "Computers": "507", "Furniture n fittings": "2906", "Railway sidings": "3688", "Vehicles": "41", "Intangible Assets": "428", "Other fixed assets": "16561", "Gross Block": "257084", "Accumulated Depreciation": "61513", "CWIP": "73618", "Investments": "23249", "Other Assets": "78923", "Inventories": "9911", "Trade receivables": "24747", "Cash Equivalents": "2747", "Loans n Advances": "3413", "Other asset items": "38104", "Total Assets": "371361"}, "Mar 2023": {"Equity Capital": "9697", "Reserves": "129193", "Borrowings": "187271", "Long term Borrowings": "156316", "Short term Borrowings": "29969", "Lease Liabilities": "986", "Other Borrowings": "0", "Other Liabilities": "57716", "Trade Payables": "9598", "Advance from Customers": "419", "Other liability items": "47699", "Total Liabilities": "383877", "Fixed Assets": "197361", "Land": "13862", "Building": "18187", "Plant Machinery": "213460", "Equipments": "1191", "Computers": "557", "Furniture n fittings": "3247", "Railway sidings": "9362", "Vehicles": "76", "Intangible Assets": "428", "Other fixed assets": "9989", "Gross Block": "270360", "Accumulated Depreciation": "72998", "CWIP": "61789", "Investments": "29770", "Other Assets": "94957", "Inventories": "13882", "Trade receivables": "26029", "Cash Equivalents": "3742", "Loans n Advances": "8096", "Other asset items": "43209", "Total Assets": "383877"}, "Mar 2024": {"Equity Capital": "9697", "Reserves": "140188", "Borrowings": "186206", "Long term Borrowings": "146159", "Short term Borrowings": "39060", "Lease Liabilities": "987", "Other Borrowings": "0", "Other Liabilities": "57439", "Trade Payables": "9475", "Advance from Customers": "637", "Other liability items": "47328", "Total Liabilities": "393530", "Fixed Assets": "212611", "Land": "14553", "Building": "19673", "Plant Machinery": "238997", "Equipments": "1379", "Computers": "583", "Furniture n fittings": "3513", "Railway sidings": "10097", "Vehicles": "33", "Intangible Assets": "0", "Other fixed assets": "11194", "Gross Block": "300021", "Accumulated Depreciation": "87410", "CWIP": "47157", "Investments": "33158", "Other Assets": "100605", "Inventories": "17606", "Trade receivables": "27348", "Cash Equivalents": "4600", "Loans n Advances": "4902", "Other asset items": "46149", "Total Assets": "393530"}, "Mar 2025": {"Equity Capital": "9697", "Reserves": "151944", "Borrowings": "186231", "Long term Borrowings": "144366", "Short term Borrowings": "40878", "Lease Liabilities": "987", "Other Borrowings": "0", "Other Liabilities": "60308", "Trade Payables": "9567", "Advance from Customers": "589", "Other liability items": "50152", "Total Liabilities": "408179", "Fixed Assets": "212208", "Land": "15040", "Building": "20669", "Plant Machinery": "251065", "Equipments": "1635", "Computers": "625", "Furniture n fittings": "3647", "Railway sidings": "10485", "Vehicles": "40", "Intangible Assets": "0", "Other fixed assets": "12098", "Gross Block": "315303", "Accumulated Depreciation": "103095", "CWIP": "52330", "Investments": "35105", "Other Assets": "108536", "Inventories": "18109", "Trade receivables": "28735", "Cash Equivalents": "4779", "Loans n Advances": "3826", "Other asset items": "53087", "Total Assets": "408179"}, "Sep 2025": {"Equity Capital": "9697", "Reserves": "158162", "Borrowings": "187142", "Long term Borrowings": "142552", "Short term Borrowings": "43514", "Lease Liabilities": "1075", "Other Borrowings": "", "Other Liabilities": "62217", "Trade Payables": "8737", "Advance from Customers": "", "Other liability items": "53480", "Total Liabilities": "417217", "Fixed Assets": "221916", "Land": "", "Building": "", "Plant Machinery": "", "Equipments": "", "Computers": "", "Furniture n fittings": "", "Railway sidings": "", "Vehicles": "", "Intangible Assets": "488", "Other fixed assets": "", "Gross Block": "", "Accumulated Depreciation": "", "CWIP": "45737", "Investments": "36248", "Other Assets": "113316", "Inventories": "15961", "Trade receivables": "25887", "Cash Equivalents": "4150", "Loans n Advances": "1836", "Other asset items": "65481", "Total Assets": "417217"}}