{"Mar 2015": {"Equity Capital": "196", "Reserves": "50439", "Borrowings": "358", "Long term Borrowings": "114", "Short term Borrowings": "186", "Lease Liabilities": "0", "Other Borrowings": "58", "Other Liabilities": "22325", "Non controlling int": "1128", "Trade Payables": "8831", "Advance from Customers": "131", "Other liability items": "12236", "Total Liabilities": "73318", "Fixed Assets": "11638", "Land": "565", "Building": "6508", "Plant Machinery": "127", "Equipments": "1769", "Computers": "5073", "Furniture n fittings": "2554", "Vehicles": "28", "Intangible Assets": "2785", "Other fixed assets": "0", "Gross Block": "19409", "Accumulated Depreciation": "7771", "CWIP": "2766", "Investments": "1662", "Other Assets": "57252", "Inventories": "16", "Trade receivables": "20438", "Cash Equivalents": "18556", "Loans n Advances": "2028", "Other asset items": "16214", "Total Assets": "73318"}, "Mar 2016": {"Equity Capital": "197", "Reserves": "70875", "Borrowings": "245", "Long term Borrowings": "83", "Short term Borrowings": "113", "Lease Liabilities": "0", "Other Borrowings": "49", "Other Liabilities": "16974", "Non controlling int": "355", "Trade Payables": "7541", "Advance from Customers": "164", "Other liability items": "8914", "Total Liabilities": "88291", "Fixed Assets": "11774", "Land": "348", "Building": "7959", "Plant Machinery": "322", "Equipments": "2004", "Computers": "5591", "Furniture n fittings": "3052", "Vehicles": "32", "Intangible Assets": "2192", "Other fixed assets": "86", "Gross Block": "21586", "Accumulated Depreciation": "9812", "CWIP": "1670", "Investments": "22822", "Other Assets": "52025", "Inventories": "16", "Trade receivables": "24073", "Cash Equivalents": "6788", "Loans n Advances": "3010", "Other asset items": "18138", "Total Assets": "88291"}, "Mar 2017": {"Equity Capital": "197", "Reserves": "86017", "Borrowings": "289", "Long term Borrowings": "71", "Short term Borrowings": "200", "Lease Liabilities": "0", "Other Borrowings": "18", "Other Liabilities": "15830", "Non controlling int": "366", "Trade Payables": "4905", "Advance from Customers": "330", "Other liability items": "10229", "Total Liabilities": "102333", "Fixed Assets": "11701", "Land": "348", "Building": "8681", "Plant Machinery": "395", "Equipments": "2112", "Computers": "6082", "Furniture n fittings": "3241", "Vehicles": "32", "Intangible Assets": "2016", "Other fixed assets": "81", "Gross Block": "22988", "Accumulated Depreciation": "11287", "CWIP": "1541", "Investments": "41980", "Other Assets": "47111", "Inventories": "21", "Trade receivables": "22617", "Cash Equivalents": "4149", "Loans n Advances": "2063", "Other asset items": "18261", "Total Assets": "102333"}, "Mar 2018": {"Equity Capital": "191", "Reserves": "84937", "Borrowings": "247", "Long term Borrowings": "54", "Short term Borrowings": "181", "Lease Liabilities": "0", "Other Borrowings": "12", "Other Liabilities": "19751", "Non controlling int": "402", "Trade Payables": "5094", "Advance from Customers": "796", "Other liability items": "13459", "Total Liabilities": "105126", "Fixed Assets": "11973", "Land": "348", "Building": "9359", "Plant Machinery": "501", "Equipments": "2221", "Computers": "6786", "Furniture n fittings": "3471", "Vehicles": "34", "Intangible Assets": "2194", "Other fixed assets": "89", "Gross Block": "25003", "Accumulated Depreciation": "13030", "CWIP": "1278", "Investments": "36008", "Other Assets": "55867", "Inventories": "26", "Trade receivables": "24943", "Cash Equivalents": "7161", "Loans n Advances": "1696", "Other asset items": "22041", "Total Assets": "105126"}, "Mar 2019": {"Equity Capital": "375", "Reserves": "89071", "Borrowings": "62", "Long term Borrowings": "44", "Short term Borrowings": "0", "Lease Liabilities": "44", "Other Borrowings": "-26", "Other Liabilities": "24393", "Non controlling int": "453", "Trade Payables": "6292", "Advance from Customers": "575", "Other liability items": "17073", "Total Liabilities": "113901", "Fixed Assets": "12290", "Land": "345", "Building": "9832", "Plant Machinery": "552", "Equipments": "2377", "Computers": "7687", "Furniture n fittings": "3690", "Vehicles": "39", "Intangible Assets": "1956", "Other fixed assets": "115", "Gross Block": "26593", "Accumulated Depreciation": "14303", "CWIP": "963", "Investments": "29330", "Other Assets": "71318", "Inventories": "10", "Trade receivables": "27346", "Cash Equivalents": "12848", "Loans n Advances": "3012", "Other asset items": "28102", "Total Assets": "113901"}, "Mar 2020": {"Equity Capital": "375", "Reserves": "83751", "Borrowings": "8174", "Long term Borrowings": "0", "Short term Borrowings": "0", "Lease Liabilities": "8174", "Other Borrowings": "0", "Other Liabilities": "27827", "Non controlling int": "623", "Trade Payables": "6740", "Advance from Customers": "345", "Other liability items": "20119", "Total Liabilities": "120127", "Fixed Assets": "20928", "Land": "1041", "Building": "18645", "Plant Machinery": "681", "Equipments": "2522", "Computers": "8824", "Furniture n fittings": "3925", "Vehicles": "68", "Intangible Assets": "2158", "Other fixed assets": "120", "Gross Block": "37984", "Accumulated Depreciation": "17056", "CWIP": "906", "Investments": "26356", "Other Assets": "71937", "Inventories": "5", "Trade receivables": "30532", "Cash Equivalents": "9666", "Loans n Advances": "1967", "Other asset items": "29767", "Total Assets": "120127"}, "Mar 2021": {"Equity Capital": "370", "Reserves": "86063", "Borrowings": "7795", "Long term Borrowings": "0", "Short term Borrowings": "0", "Lease Liabilities": "7795", "Other Borrowings": "0", "Other Liabilities": "35764", "Non controlling int": "675", "Trade Payables": "7860", "Advance from Customers": "312", "Other liability items": "26917", "Total Liabilities": "129992", "Fixed Assets": "21021", "Land": "1041", "Building": "18524", "Plant Machinery": "737", "Equipments": "2587", "Computers": "10873", "Furniture n fittings": "3943", "Vehicles": "86", "Intangible Assets": "2538", "Other fixed assets": "122", "Gross Block": "40451", "Accumulated Depreciation": "19430", "CWIP": "926", "Investments": "29373", "Other Assets": "78672", "Inventories": "8", "Trade receivables": "30079", "Cash Equivalents": "9329", "Loans n Advances": "5107", "Other asset items": "34149", "Total Assets": "129992"}, "Mar 2022": {"Equity Capital": "366", "Reserves": "88773", "Borrowings": "7818", "Long term Borrowings": "0", "Short term Borrowings": "0", "Lease Liabilities": "7818", "Other Borrowings": "0", "Other Liabilities": "43967", "Non controlling int": "707", "Trade Payables": "8045", "Advance from Customers": "468", "Other liability items": "34747", "Total Liabilities": "140924", "Fixed Assets": "21298", "Land": "1126", "Building": "17007", "Plant Machinery": "770", "Equipments": "2693", "Computers": "12301", "Furniture n fittings": "3968", "Vehicles": "71", "Intangible Assets": "3484", "Other fixed assets": "121", "Gross Block": "41541", "Accumulated Depreciation": "20243", "CWIP": "1205", "Investments": "30485", "Other Assets": "87936", "Inventories": "20", "Trade receivables": "41810", "Cash Equivalents": "18221", "Loans n Advances": "3600", "Other asset items": "24285", "Total Assets": "140924"}, "Mar 2023": {"Equity Capital": "366", "Reserves": "90058", "Borrowings": "7688", "Long term Borrowings": "0", "Short term Borrowings": "0", "Lease Liabilities": "7688", "Other Borrowings": "0", "Other Liabilities": "44747", "Non controlling int": "782", "Trade Payables": "10515", "Advance from Customers": "543", "Other liability items": "32907", "Total Liabilities": "142859", "Fixed Assets": "20515", "Land": "1304", "Building": "18635", "Plant Machinery": "828", "Equipments": "2823", "Computers": "13725", "Furniture n fittings": "4130", "Vehicles": "93", "Intangible Assets": "3750", "Other fixed assets": "126", "Gross Block": "45414", "Accumulated Depreciation": "24899", "CWIP": "1234", "Investments": "37163", "Other Assets": "83947", "Inventories": "28", "Trade receivables": "49954", "Cash Equivalents": "11032", "Loans n Advances": "2097", "Other asset items": "20836", "Total Assets": "142859"}, "Mar 2024": {"Equity Capital": "362", "Reserves": "90127", "Borrowings": "8021", "Long term Borrowings": "0", "Short term Borrowings": "0", "Lease Liabilities": "8021", "Other Borrowings": "0", "Other Liabilities": "46962", "Non controlling int": "830", "Trade Payables": "9981", "Advance from Customers": "1841", "Other liability items": "34310", "Total Liabilities": "145472", "Fixed Assets": "19604", "Land": "1294", "Building": "19314", "Plant Machinery": "878", "Equipments": "2982", "Computers": "14544", "Furniture n fittings": "4346", "Vehicles": "97", "Intangible Assets": "3836", "Other fixed assets": "127", "Gross Block": "47418", "Accumulated Depreciation": "27814", "CWIP": "1564", "Investments": "31762", "Other Assets": "92542", "Inventories": "28", "Trade receivables": "53577", "Cash Equivalents": "13286", "Loans n Advances": "3989", "Other asset items": "21662", "Total Assets": "145472"}, "Mar 2025": {"Equity Capital": "362", "Reserves": "94394", "Borrowings": "9392", "Long term Borrowings": "0", "Short term Borrowings": "0", "Lease Liabilities": "9392", "Other Borrowings": "0", "Other Liabilities": "54501", "Non controlling int": "1015", "Trade Payables": "13909", "Advance from Customers": "1896", "Other liability items": "37681", "Total Liabilities": "158649", "Fixed Assets": "23053", "Land": "2873", "Building": "19681", "Plant Machinery": "993", "Equipments": "3166", "Computers": "15123", "Furniture n fittings": "4628", "Vehicles": "88", "Intangible Assets": "4865", "Other fixed assets": "129", "Gross Block": "51546", "Accumulated Depreciation": "28493", "CWIP": "1546", "Investments": "30964", "Other Assets": "103086", "Inventories": "21", "Trade receivables": "59046", "Cash Equivalents": "15463", "Loans n Advances": "4612", "Other asset items": "23944", "Total Assets": "158649"}, "Mar 2026": {"Equity Capital": "362", "Reserves": "106878", "Borrowings": "11283", "Long term Borrowings": "0", "Short term Borrowings": "0", "Lease Liabilities": "11283", "Other Borrowings": "0", "Other Liabilities": "62644", "Non controlling int": "1238", "Trade Payables": "14808", "Advance from Customers": "694", "Other liability items": "45904", "Total Liabilities": "181167", "Fixed Assets": "31343", "Land": "2873", "Building": "21834", "Plant Machinery": "1039", "Equipments": "3390", "Computers": "16159", "Furniture n fittings": "4840", "Vehicles": "100", "Intangible Assets": "10284", "Other fixed assets": "228", "Gross Block": "60747", "Accumulated Depreciation": "29404", "CWIP": "2665", "Investments": "33988", "Other Assets": "113171", "Inventories": "29", "Trade receivables": "67714", "Cash Equivalents": "12908", "Loans n Advances": "6433", "Other asset items": "26087", "Total Assets": "181167"}}