{"Mar 2014": {"Sales": "212", "Sales Growth %": "", "Expenses": "193", "Material Cost %": "70%", "Manufacturing Cost %": "8%", "Employee Cost %": "4%", "Other Cost %": "8%", "Operating Profit": "20", "OPM %": "9%", "Other Income": "3", "Exceptional items": "-0.00", "Other income normal": "2.51", "Interest": "3", "Depreciation": "2", "Profit before tax": "17", "Tax %": "19%", "Net Profit": "14", "Minority share": "-0.78", "Exceptional items AT": "0.00", "Profit excl Excep": "14.21", "Profit for PE": "13.43", "Profit for EPS": "13.43", "Profit Growth %": "", "EPS in Rs": "1.56", "Dividend Payout %": "0%"}, "Mar 2015": {"Sales": "236", "Sales Growth %": "10.96%", "Expenses": "216", "Material Cost %": "71%", "Manufacturing Cost %": "7%", "Employee Cost %": "6%", "Other Cost %": "7%", "Operating Profit": "20", "OPM %": "8%", "Other Income": "3", "Exceptional items": "-0.00", "Other income normal": "2.77", "Interest": "5", "Depreciation": "6", "Profit before tax": "12", "Tax %": "29%", "Net Profit": "9", "Minority share": "-0.64", "Exceptional items AT": "0.00", "Profit excl Excep": "8.51", "Profit for PE": "7.87", "Profit for EPS": "7.87", "Profit Growth %": "-41.40%", "EPS in Rs": "0.92", "Dividend Payout %": "0%"}, "Mar 2016": {"Sales": "250", "Sales Growth %": "6.01%", "Expenses": "229", "Material Cost %": "67%", "Manufacturing Cost %": "9%", "Employee Cost %": "6%", "Other Cost %": "9%", "Operating Profit": "21", "OPM %": "8%", "Other Income": "2", "Exceptional items": "-0.00", "Other income normal": "1.92", "Interest": "3", "Depreciation": "5", "Profit before tax": "14", "Tax %": "34%", "Net Profit": "9", "Minority share": "-0.14", "Exceptional items AT": "0.00", "Profit excl Excep": "9.35", "Profit for PE": "9.21", "Profit for EPS": "9.21", "Profit Growth %": "17.03%", "EPS in Rs": "1.07", "Dividend Payout %": "0%"}, "Mar 2017": {"Sales": "272", "Sales Growth %": "8.72%", "Expenses": "246", "Material Cost %": "66%", "Manufacturing Cost %": "11%", "Employee Cost %": "6%", "Other Cost %": "8%", "Operating Profit": "26", "OPM %": "9%", "Other Income": "2", "Exceptional items": "-0.00", "Other income normal": "2.08", "Interest": "5", "Depreciation": "5", "Profit before tax": "18", "Tax %": "38%", "Net Profit": "11", "Minority share": "-0.58", "Exceptional items AT": "0.00", "Profit excl Excep": "10.80", "Profit for PE": "10.22", "Profit for EPS": "10.22", "Profit Growth %": "10.97%", "EPS in Rs": "1.19", "Dividend Payout %": "0%"}, "Mar 2018": {"Sales": "369", "Sales Growth %": "35.80%", "Expenses": "337", "Material Cost %": "78%", "Manufacturing Cost %": "1%", "Employee Cost %": "8%", "Other Cost %": "5%", "Operating Profit": "31", "OPM %": "9%", "Other Income": "3", "Exceptional items": "-0.04", "Other income normal": "2.98", "Interest": "7", "Depreciation": "5", "Profit before tax": "23", "Tax %": "28%", "Net Profit": "16", "Minority share": "-0.50", "Exceptional items AT": "-0.03", "Profit excl Excep": "16.29", "Profit for PE": "15.79", "Profit for EPS": "15.76", "Profit Growth %": "54.49%", "EPS in Rs": "1.75", "Dividend Payout %": "0%"}, "Mar 2019": {"Sales": "400", "Sales Growth %": "8.42%", "Expenses": "378", "Material Cost %": "79%", "Manufacturing Cost %": "2%", "Employee Cost %": "7%", "Other Cost %": "6%", "Operating Profit": "22", "OPM %": "6%", "Other Income": "4", "Exceptional items": "-0.04", "Other income normal": "3.94", "Interest": "8", "Depreciation": "5", "Profit before tax": "13", "Tax %": "29%", "Net Profit": "9", "Minority share": "0.06", "Exceptional items AT": "-0.02", "Profit excl Excep": "9.18", "Profit for PE": "9.24", "Profit for EPS": "9.22", "Profit Growth %": "-41.48%", "EPS in Rs": "0.75", "Dividend Payout %": "0%"}, "Mar 2020": {"Sales": "263", "Sales Growth %": "-34.24%", "Expenses": "240", "Material Cost %": "71%", "Manufacturing Cost %": "2%", "Employee Cost %": "12%", "Other Cost %": "7%", "Operating Profit": "22", "OPM %": "9%", "Other Income": "6", "Exceptional items": "-0.18", "Other income normal": "6.07", "Interest": "11", "Depreciation": "10", "Profit before tax": "8", "Tax %": "24%", "Net Profit": "6", "Minority share": "-0.27", "Exceptional items AT": "-0.11", "Profit excl Excep": "5.99", "Profit for PE": "5.71", "Profit for EPS": "5.61", "Profit Growth %": "-38.15%", "EPS in Rs": "0.46", "Dividend Payout %": "0%"}, "Mar 2021": {"Sales": "251", "Sales Growth %": "-4.43%", "Expenses": "224", "Material Cost %": "69%", "Manufacturing Cost %": "2%", "Employee Cost %": "10%", "Other Cost %": "8%", "Operating Profit": "27", "OPM %": "11%", "Other Income": "8", "Exceptional items": "0.10", "Other income normal": "7.63", "Interest": "9", "Depreciation": "9", "Profit before tax": "17", "Tax %": "20%", "Net Profit": "14", "Minority share": "-0.63", "Exceptional items AT": "0.08", "Profit excl Excep": "13.45", "Profit for PE": "12.82", "Profit for EPS": "12.90", "Profit Growth %": "124.39%", "EPS in Rs": "1.05", "Dividend Payout %": "19%"}, "Mar 2022": {"Sales": "376", "Sales Growth %": "49.76%", "Expenses": "344", "Material Cost %": "75%", "Manufacturing Cost %": "2%", "Employee Cost %": "8%", "Other Cost %": "6%", "Operating Profit": "32", "OPM %": "9%", "Other Income": "4", "Exceptional items": "-0.86", "Other income normal": "4.85", "Interest": "7", "Depreciation": "9", "Profit before tax": "19", "Tax %": "32%", "Net Profit": "13", "Minority share": "-0.30", "Exceptional items AT": "-0.58", "Profit excl Excep": "13.86", "Profit for PE": "13.55", "Profit for EPS": "12.98", "Profit Growth %": "5.64%", "EPS in Rs": "1.06", "Dividend Payout %": "0%"}, "Mar 2023": {"Sales": "443", "Sales Growth %": "17.68%", "Expenses": "404", "Material Cost %": "74%", "Manufacturing Cost %": "2%", "Employee Cost %": "8%", "Other Cost %": "7%", "Operating Profit": "39", "OPM %": "9%", "Other Income": "5", "Exceptional items": "0.41", "Other income normal": "4.12", "Interest": "10", "Depreciation": "8", "Profit before tax": "25", "Tax %": "33%", "Net Profit": "17", "Minority share": "0.19", "Exceptional items AT": "0.27", "Profit excl Excep": "16.54", "Profit for PE": "16.73", "Profit for EPS": "17.00", "Profit Growth %": "23.50%", "EPS in Rs": "1.35", "Dividend Payout %": "0%"}, "Mar 2024": {"Sales": "622", "Sales Growth %": "40.48%", "Expenses": "570", "Material Cost %": "76%", "Manufacturing Cost %": "2%", "Employee Cost %": "7%", "Other Cost %": "7%", "Operating Profit": "52", "OPM %": "8%", "Other Income": "7", "Exceptional items": "-0.00", "Other income normal": "7.29", "Interest": "12", "Depreciation": "10", "Profit before tax": "36", "Tax %": "29%", "Net Profit": "26", "Minority share": "0.14", "Exceptional items AT": "0.00", "Profit excl Excep": "25.76", "Profit for PE": "25.90", "Profit for EPS": "25.90", "Profit Growth %": "54.81%", "EPS in Rs": "1.95", "Dividend Payout %": "10%"}, "Mar 2025": {"Sales": "767", "Sales Growth %": "23.30%", "Expenses": "698", "Material Cost %": "73%", "Manufacturing Cost %": "2%", "Employee Cost %": "7%", "Other Cost %": "9%", "Operating Profit": "69", "OPM %": "9%", "Other Income": "13", "Exceptional items": "0.98", "Other income normal": "12.37", "Interest": "14", "Depreciation": "16", "Profit before tax": "52", "Tax %": "27%", "Net Profit": "38", "Minority share": "0.32", "Exceptional items AT": "0.63", "Profit excl Excep": "37.48", "Profit for PE": "37.80", "Profit for EPS": "38.43", "Profit Growth %": "45.95%", "EPS in Rs": "2.79", "Dividend Payout %": "11%"}, "TTM": {"Sales": "850", "Sales Growth %": "0", "Expenses": "765", "Material Cost %": "0", "Manufacturing Cost %": "0", "Employee Cost %": "0", "Other Cost %": "0", "Operating Profit": "85", "OPM %": "10%", "Other Income": "17", "Exceptional items": "0", "Other income normal": "0", "Interest": "15", "Depreciation": "15", "Profit before tax": "72", "Tax %": "", "Net Profit": "54", "Minority share": "0", "Exceptional items AT": "0", "Profit excl Excep": "0", "Profit for PE": "0", "Profit for EPS": "0", "Profit Growth %": "0", "EPS in Rs": "3.86", "Dividend Payout %": ""}}