{"Mar 2014": {"Equity Capital": "14", "Reserves": "138", "Borrowings": "96", "Long term Borrowings": "11", "Short term Borrowings": "78", "Lease Liabilities": "0", "Other Borrowings": "7", "Other Liabilities": "407", "Non controlling int": "8", "Trade Payables": "315", "Advance from Customers": "41", "Other liability items": "42", "Total Liabilities": "655", "Fixed Assets": "94", "Land": "5.82", "Building": "56.41", "Plant Machinery": "98.52", "Equipments": "22.09", "Furniture n fittings": "11.99", "Vehicles": "5.39", "Intangible Assets": "1.18", "Other fixed assets": "4.40", "Gross Block": "205.80", "Accumulated Depreciation": "112.16", "CWIP": "1", "Investments": "3", "Other Assets": "557", "Inventories": "75", "Trade receivables": "348", "Cash Equivalents": "24", "Loans n Advances": "19", "Other asset items": "90", "Total Assets": "655"}, "Mar 2015": {"Equity Capital": "14", "Reserves": "142", "Borrowings": "86", "Long term Borrowings": "20", "Short term Borrowings": "57", "Lease Liabilities": "0", "Other Borrowings": "9", "Other Liabilities": "437", "Non controlling int": "8", "Trade Payables": "316", "Advance from Customers": "47", "Other liability items": "65", "Total Liabilities": "679", "Fixed Assets": "85", "Land": "5.82", "Building": "56.59", "Plant Machinery": "102.53", "Equipments": "23.19", "Furniture n fittings": "12.01", "Vehicles": "5.78", "Intangible Assets": "1.18", "Other fixed assets": "4.82", "Gross Block": "211.92", "Accumulated Depreciation": "127.38", "CWIP": "14", "Investments": "2", "Other Assets": "578", "Inventories": "79", "Trade receivables": "358", "Cash Equivalents": "26", "Loans n Advances": "21", "Other asset items": "94", "Total Assets": "679"}, "Mar 2016": {"Equity Capital": "14", "Reserves": "156", "Borrowings": "90", "Long term Borrowings": "23", "Short term Borrowings": "57", "Lease Liabilities": "0", "Other Borrowings": "10", "Other Liabilities": "456", "Non controlling int": "6", "Trade Payables": "331", "Advance from Customers": "43", "Other liability items": "75", "Total Liabilities": "715", "Fixed Assets": "103", "Land": "5.82", "Building": "62.63", "Plant Machinery": "121.08", "Equipments": "25.23", "Furniture n fittings": "12.42", "Vehicles": "5.94", "Intangible Assets": "1.18", "Other fixed assets": "5.37", "Gross Block": "239.67", "Accumulated Depreciation": "136.72", "CWIP": "2", "Investments": "2", "Other Assets": "608", "Inventories": "81", "Trade receivables": "363", "Cash Equivalents": "33", "Loans n Advances": "16", "Other asset items": "114", "Total Assets": "715"}, "Mar 2017": {"Equity Capital": "14", "Reserves": "153", "Borrowings": "111", "Long term Borrowings": "30", "Short term Borrowings": "68", "Lease Liabilities": "0", "Other Borrowings": "13", "Other Liabilities": "689", "Non controlling int": "4", "Trade Payables": "391", "Advance from Customers": "221", "Other liability items": "73", "Total Liabilities": "967", "Fixed Assets": "99", "Land": "6.96", "Building": "39.19", "Plant Machinery": "52.66", "Equipments": "5.11", "Furniture n fittings": "2.45", "Vehicles": "2.37", "Intangible Assets": "0.00", "Other fixed assets": "1.78", "Gross Block": "110.52", "Accumulated Depreciation": "11.56", "CWIP": "34", "Investments": "3", "Other Assets": "831", "Inventories": "129", "Trade receivables": "416", "Cash Equivalents": "168", "Loans n Advances": "37", "Other asset items": "81", "Total Assets": "967"}, "Mar 2018": {"Equity Capital": "14", "Reserves": "186", "Borrowings": "165", "Long term Borrowings": "33", "Short term Borrowings": "113", "Lease Liabilities": "0", "Other Borrowings": "19", "Other Liabilities": "699", "Non controlling int": "3", "Trade Payables": "364", "Advance from Customers": "254", "Other liability items": "78", "Total Liabilities": "1064", "Fixed Assets": "145", "Land": "7.02", "Building": "54.12", "Plant Machinery": "89.16", "Equipments": "7.86", "Furniture n fittings": "4.82", "Vehicles": "4.17", "Intangible Assets": "0.00", "Other fixed assets": "2.21", "Gross Block": "169.36", "Accumulated Depreciation": "24.49", "CWIP": "7", "Investments": "4", "Other Assets": "909", "Inventories": "101", "Trade receivables": "437", "Cash Equivalents": "263", "Loans n Advances": "22", "Other asset items": "85", "Total Assets": "1064"}, "Mar 2019": {"Equity Capital": "14", "Reserves": "246", "Borrowings": "110", "Long term Borrowings": "26", "Short term Borrowings": "67", "Lease Liabilities": "0", "Other Borrowings": "17", "Other Liabilities": "795", "Non controlling int": "2", "Trade Payables": "415", "Advance from Customers": "292", "Other liability items": "85", "Total Liabilities": "1164", "Fixed Assets": "161", "Land": "7.02", "Building": "55.54", "Plant Machinery": "108.50", "Equipments": "11.17", "Furniture n fittings": "5.61", "Vehicles": "4.47", "Intangible Assets": "8.63", "Other fixed assets": "2.74", "Gross Block": "203.68", "Accumulated Depreciation": "43.02", "CWIP": "12", "Investments": "5", "Other Assets": "987", "Inventories": "130", "Trade receivables": "424", "Cash Equivalents": "290", "Loans n Advances": "49", "Other asset items": "94", "Total Assets": "1164"}, "Mar 2020": {"Equity Capital": "14", "Reserves": "349", "Borrowings": "122", "Long term Borrowings": "19", "Short term Borrowings": "72", "Lease Liabilities": "20", "Other Borrowings": "11", "Other Liabilities": "896", "Non controlling int": "2", "Trade Payables": "494", "Advance from Customers": "215", "Other liability items": "185", "Total Liabilities": "1382", "Fixed Assets": "194", "Land": "6.79", "Building": "77.39", "Plant Machinery": "131.66", "Equipments": "13.20", "Furniture n fittings": "6.40", "Vehicles": "5.37", "Intangible Assets": "8.63", "Other fixed assets": "3.51", "Gross Block": "252.95", "Accumulated Depreciation": "58.91", "CWIP": "12", "Investments": "5", "Other Assets": "1172", "Inventories": "134", "Trade receivables": "502", "Cash Equivalents": "373", "Loans n Advances": "58", "Other asset items": "104", "Total Assets": "1382"}, "Mar 2021": {"Equity Capital": "14", "Reserves": "492", "Borrowings": "62", "Long term Borrowings": "8", "Short term Borrowings": "43", "Lease Liabilities": "11", "Other Borrowings": "0", "Other Liabilities": "875", "Non controlling int": "-0", "Trade Payables": "535", "Advance from Customers": "126", "Other liability items": "214", "Total Liabilities": "1443", "Fixed Assets": "190", "Land": "6.79", "Building": "84.10", "Plant Machinery": "144.18", "Equipments": "15.13", "Furniture n fittings": "7.36", "Vehicles": "5.45", "Intangible Assets": "8.63", "Other fixed assets": "4.67", "Gross Block": "276.31", "Accumulated Depreciation": "86.58", "CWIP": "15", "Investments": "5", "Other Assets": "1234", "Inventories": "128", "Trade receivables": "449", "Cash Equivalents": "505", "Loans n Advances": "36", "Other asset items": "116", "Total Assets": "1443"}, "Mar 2022": {"Equity Capital": "14", "Reserves": "641", "Borrowings": "55", "Long term Borrowings": "12", "Short term Borrowings": "36", "Lease Liabilities": "7", "Other Borrowings": "0", "Other Liabilities": "914", "Non controlling int": "-1", "Trade Payables": "523", "Advance from Customers": "215", "Other liability items": "176", "Total Liabilities": "1625", "Fixed Assets": "192", "Land": "18.24", "Building": "86.55", "Plant Machinery": "152.80", "Equipments": "18.55", "Furniture n fittings": "7.90", "Vehicles": "5.59", "Intangible Assets": "8.63", "Other fixed assets": "5.08", "Gross Block": "303.34", "Accumulated Depreciation": "111.24", "CWIP": "20", "Investments": "9", "Other Assets": "1404", "Inventories": "181", "Trade receivables": "508", "Cash Equivalents": "536", "Loans n Advances": "45", "Other asset items": "135", "Total Assets": "1625"}, "Mar 2023": {"Equity Capital": "14", "Reserves": "819", "Borrowings": "59", "Long term Borrowings": "16", "Short term Borrowings": "37", "Lease Liabilities": "7", "Other Borrowings": "0", "Other Liabilities": "1047", "Non controlling int": "2", "Trade Payables": "551", "Advance from Customers": "195", "Other liability items": "298", "Total Liabilities": "1939", "Fixed Assets": "215", "Land": "18.92", "Building": "95.86", "Plant Machinery": "185.67", "Equipments": "23.57", "Furniture n fittings": "9.07", "Vehicles": "6.76", "Intangible Assets": "8.63", "Other fixed assets": "5.57", "Gross Block": "354.05", "Accumulated Depreciation": "138.63", "CWIP": "42", "Investments": "10", "Other Assets": "1672", "Inventories": "222", "Trade receivables": "697", "Cash Equivalents": "548", "Loans n Advances": "35", "Other asset items": "170", "Total Assets": "1939"}, "Mar 2024": {"Equity Capital": "14", "Reserves": "1004", "Borrowings": "152", "Long term Borrowings": "109", "Short term Borrowings": "29", "Lease Liabilities": "15", "Other Borrowings": "-0", "Other Liabilities": "1271", "Non controlling int": "2", "Trade Payables": "695", "Advance from Customers": "183", "Other liability items": "391", "Total Liabilities": "2441", "Fixed Assets": "367", "Land": "57.50", "Building": "147.27", "Plant Machinery": "243.63", "Equipments": "34.12", "Furniture n fittings": "11.88", "Vehicles": "10.79", "Intangible Assets": "10.21", "Other fixed assets": "20.88", "Gross Block": "536.28", "Accumulated Depreciation": "169.74", "CWIP": "61", "Investments": "12", "Other Assets": "2001", "Inventories": "237", "Trade receivables": "935", "Cash Equivalents": "588", "Loans n Advances": "54", "Other asset items": "188", "Total Assets": "2441"}, "Mar 2025": {"Equity Capital": "14", "Reserves": "1194", "Borrowings": "323", "Long term Borrowings": "252", "Short term Borrowings": "51", "Lease Liabilities": "20", "Other Borrowings": "-0", "Other Liabilities": "1449", "Non controlling int": "2", "Trade Payables": "779", "Advance from Customers": "248", "Other liability items": "420", "Total Liabilities": "2979", "Fixed Assets": "392", "Land": "58.72", "Building": "180.50", "Plant Machinery": "264.68", "Equipments": "41.44", "Furniture n fittings": "13.06", "Vehicles": "11.92", "Intangible Assets": "10.21", "Other fixed assets": "22.44", "Gross Block": "602.97", "Accumulated Depreciation": "210.72", "CWIP": "323", "Investments": "13", "Other Assets": "2250", "Inventories": "299", "Trade receivables": "1134", "Cash Equivalents": "466", "Loans n Advances": "72", "Other asset items": "280", "Total Assets": "2979"}, "Sep 2025": {"Equity Capital": "14", "Reserves": "1278", "Borrowings": "421", "Long term Borrowings": "346", "Short term Borrowings": "55", "Lease Liabilities": "20", "Other Borrowings": "", "Other Liabilities": "1397", "Non controlling int": "2", "Trade Payables": "728", "Advance from Customers": "", "Other liability items": "667", "Total Liabilities": "3110", "Fixed Assets": "640", "Land": "", "Building": "", "Plant Machinery": "", "Equipments": "", "Furniture n fittings": "", "Vehicles": "", "Intangible Assets": "24.73", "Other fixed assets": "", "Gross Block": "", "Accumulated Depreciation": "", "CWIP": "203", "Investments": "14", "Other Assets": "2254", "Inventories": "386", "Trade receivables": "1045", "Cash Equivalents": "390", "Loans n Advances": "28", "Other asset items": "405", "Total Assets": "3110"}}