{"1774915200000":{"TaxEffectOfUnusualItems":0.0,"TaxRateForCalcs":0.247815,"TotalUnusualItems":0.0,"TotalUnusualItemsExcludingGoodwill":0.0,"NetIncomeFromContinuingOperationNetMinorityInterest":100247100000.0,"ReconciledDepreciation":6989000000.0,"NetInterestIncome":251368000000.0,"InterestExpense":215210200000.0,"InterestIncome":466578200000.0,"NormalizedIncome":100247100000.0,"NetIncomeFromContinuingAndDiscontinuedOperation":100241600000.0,"DilutedAverageShares":null,"BasicAverageShares":null,"DilutedEPS":null,"BasicEPS":null,"DilutedNIAvailtoComStockholders":100241600000.0,"NetIncomeCommonStockholders":100241600000.0,"NetIncome":100241600000.0,"MinorityInterests":100000.0,"NetIncomeIncludingNoncontrollingInterests":100241500000.0,"NetIncomeDiscontinuousOperations":-5500000.0,"NetIncomeContinuousOperations":100247000000.0,"TaxProvision":32959900000.0,"PretaxIncome":133001900000.0,"SpecialIncomeCharges":0.0,"OtherSpecialCharges":null,"WriteOff":null,"GainOnSaleOfSecurity":3549500000.0,"OperatingExpense":74359500000.0,"OtherOperatingExpenses":26063300000.0,"DepreciationAndAmortizationInIncomeStatement":6989000000.0,"Amortization":null,"DepreciationIncomeStatement":6989000000.0,"SellingGeneralAndAdministration":null,"SellingAndMarketingExpense":null,"GeneralAndAdministrativeExpense":null,"InsuranceAndClaims":null,"RentAndLandingFees":null,"TotalRevenue":260750900000.0,"OperatingRevenue":260750900000.0},"1743379200000":{"TaxEffectOfUnusualItems":3826830182.7334599495,"TaxRateForCalcs":0.246311,"TotalUnusualItems":15536600000.0,"TotalUnusualItemsExcludingGoodwill":15536600000.0,"NetIncomeFromContinuingOperationNetMinorityInterest":94131200000.0,"ReconciledDepreciation":6453200000.0,"NetInterestIncome":218530600000.0,"InterestExpense":184545800000.0,"InterestIncome":403076400000.0,"NormalizedIncome":82421430182.7334594727,"NetIncomeFromContinuingAndDiscontinuedOperation":95538200000.0,"DilutedAverageShares":1882526108.0,"BasicAverageShares":1879933097.0,"DilutedEPS":50.75,"BasicEPS":50.82,"DilutedNIAvailtoComStockholders":95538200000.0,"NetIncomeCommonStockholders":95538200000.0,"NetIncome":95538200000.0,"MinorityInterests":-225000000.0,"NetIncomeIncludingNoncontrollingInterests":95763200000.0,"NetIncomeDiscontinuousOperations":1407000000.0,"NetIncomeContinuousOperations":94356200000.0,"TaxProvision":30796000000.0,"PretaxIncome":125029100000.0,"SpecialIncomeCharges":15536600000.0,"OtherSpecialCharges":-15536600000.0,"WriteOff":17000000.0,"GainOnSaleOfSecurity":3335800000.0,"OperatingExpense":65715200000.0,"OtherOperatingExpenses":22750400000.0,"DepreciationAndAmortizationInIncomeStatement":6453200000.0,"Amortization":3654600000.0,"DepreciationIncomeStatement":6453200000.0,"SellingGeneralAndAdministration":7360000000.0,"SellingAndMarketingExpense":4890800000.0,"GeneralAndAdministrativeExpense":2469200000.0,"InsuranceAndClaims":76600000.0,"RentAndLandingFees":152600000.0,"TotalRevenue":228324300000.0,"OperatingRevenue":228324300000.0},"1711843200000":{"TaxEffectOfUnusualItems":-4635000.0,"TaxRateForCalcs":0.2575,"TotalUnusualItems":-18000000.0,"TotalUnusualItemsExcludingGoodwill":-18000000.0,"NetIncomeFromContinuingOperationNetMinorityInterest":71657500000.0,"ReconciledDepreciation":5688300000.0,"NetInterestIncome":188054000000.0,"InterestExpense":148026000000.0,"InterestIncome":336080000000.0,"NormalizedIncome":71670865000.0,"NetIncomeFromContinuingAndDiscontinuedOperation":73663800000.0,"DilutedAverageShares":1882100000.0,"BasicAverageShares":1876100000.0,"DilutedEPS":39.14,"BasicEPS":39.26,"DilutedNIAvailtoComStockholders":73663800000.0,"NetIncomeCommonStockholders":73663800000.0,"NetIncome":73663800000.0,"MinorityInterests":-325100000.0,"NetIncomeIncludingNoncontrollingInterests":73988900000.0,"NetIncomeDiscontinuousOperations":2006300000.0,"NetIncomeContinuousOperations":71982600000.0,"TaxProvision":24931600000.0,"PretaxIncome":96836400000.0,"SpecialIncomeCharges":-18000000.0,"OtherSpecialCharges":-12600000.0,"WriteOff":30600000.0,"GainOnSaleOfSecurity":5159500000.0,"OperatingExpense":55364400000.0,"OtherOperatingExpenses":12241600000.0,"DepreciationAndAmortizationInIncomeStatement":5688300000.0,"Amortization":3295200000.0,"DepreciationIncomeStatement":2393100000.0,"SellingGeneralAndAdministration":5053100000.0,"SellingAndMarketingExpense":3213100000.0,"GeneralAndAdministrativeExpense":1840000000.0,"InsuranceAndClaims":78400000.0,"RentAndLandingFees":128600000.0,"TotalRevenue":190834000000.0,"OperatingRevenue":190834000000.0},"1680220800000":{"TaxEffectOfUnusualItems":-101931620.0,"TaxRateForCalcs":0.2681,"TotalUnusualItems":-380200000.0,"TotalUnusualItemsExcludingGoodwill":-380200000.0,"NetIncomeFromContinuingOperationNetMinorityInterest":60110400000.0,"ReconciledDepreciation":6006900000.0,"NetInterestIncome":162894900000.0,"InterestExpense":129312700000.0,"InterestIncome":292207600000.0,"NormalizedIncome":60388668380.0,"NetIncomeFromContinuingAndDiscontinuedOperation":60110400000.0,"DilutedAverageShares":1880500000.0,"BasicAverageShares":1872000000.0,"DilutedEPS":31.966,"BasicEPS":32.108,"DilutedNIAvailtoComStockholders":60110400000.0,"NetIncomeCommonStockholders":60110400000.0,"NetIncome":60110400000.0,"MinorityInterests":-89900000.0,"NetIncomeIncludingNoncontrollingInterests":60200300000.0,"NetIncomeDiscontinuousOperations":null,"NetIncomeContinuousOperations":60200300000.0,"TaxProvision":22022500000.0,"PretaxIncome":82137200000.0,"SpecialIncomeCharges":-380200000.0,"OtherSpecialCharges":10000000.0,"WriteOff":370200000.0,"GainOnSaleOfSecurity":10071100000.0,"OperatingExpense":48361100000.0,"OtherOperatingExpenses":11403300000.0,"DepreciationAndAmortizationInIncomeStatement":6006900000.0,"Amortization":null,"DepreciationIncomeStatement":6006900000.0,"SellingGeneralAndAdministration":4407500000.0,"SellingAndMarketingExpense":2218100000.0,"GeneralAndAdministrativeExpense":2189400000.0,"InsuranceAndClaims":78800000.0,"RentAndLandingFees":76400000.0,"TotalRevenue":169309900000.0,"OperatingRevenue":169309900000.0},"1648684800000":{"TaxEffectOfUnusualItems":null,"TaxRateForCalcs":null,"TotalUnusualItems":null,"TotalUnusualItemsExcludingGoodwill":null,"NetIncomeFromContinuingOperationNetMinorityInterest":null,"ReconciledDepreciation":null,"NetInterestIncome":null,"InterestExpense":null,"InterestIncome":null,"NormalizedIncome":null,"NetIncomeFromContinuingAndDiscontinuedOperation":null,"DilutedAverageShares":1331000000.0,"BasicAverageShares":1331000000.0,"DilutedEPS":20.446,"BasicEPS":20.446,"DilutedNIAvailtoComStockholders":null,"NetIncomeCommonStockholders":null,"NetIncome":null,"MinorityInterests":null,"NetIncomeIncludingNoncontrollingInterests":null,"NetIncomeDiscontinuousOperations":null,"NetIncomeContinuousOperations":null,"TaxProvision":null,"PretaxIncome":null,"SpecialIncomeCharges":null,"OtherSpecialCharges":7900000.0,"WriteOff":18400000.0,"GainOnSaleOfSecurity":null,"OperatingExpense":null,"OtherOperatingExpenses":null,"DepreciationAndAmortizationInIncomeStatement":null,"Amortization":null,"DepreciationIncomeStatement":null,"SellingGeneralAndAdministration":2132000000.0,"SellingAndMarketingExpense":1004700000.0,"GeneralAndAdministrativeExpense":1127300000.0,"InsuranceAndClaims":20300000.0,"RentAndLandingFees":32400000.0,"TotalRevenue":null,"OperatingRevenue":null}}