{"1767139200000":{"TaxEffectOfUnusualItems":0.0,"TaxRateForCalcs":0.302745,"NormalizedEBITDA":1079260000.0,"NetIncomeFromContinuingOperationNetMinorityInterest":545560000.0,"ReconciledDepreciation":288850000.0,"ReconciledCostOfRevenue":4994830000.0,"EBITDA":1079260000.0,"EBIT":790410000.0,"NetInterestIncome":-7970000.0,"InterestExpense":7970000.0,"NormalizedIncome":545560000.0,"NetIncomeFromContinuingAndDiscontinuedOperation":545560000.0,"TotalExpenses":7077810000.0,"DilutedAverageShares":75249655.0,"BasicAverageShares":75249655.0,"DilutedEPS":7.25,"BasicEPS":7.25,"DilutedNIAvailtoComStockholders":545560000.0,"NetIncomeCommonStockholders":545560000.0,"OtherunderPreferredStockDividend":0.0,"NetIncome":545560000.0,"NetIncomeIncludingNoncontrollingInterests":545560000.0,"NetIncomeContinuousOperations":545560000.0,"TaxProvision":236880000.0,"PretaxIncome":782440000.0,"OtherNonOperatingIncomeExpenses":71530000.0,"NetNonOperatingInterestIncomeExpense":-7970000.0,"InterestExpenseNonOperating":7970000.0,"OperatingIncome":718880000.0,"OperatingExpense":2082980000.0,"OtherOperatingExpenses":1301930000.0,"DepreciationAndAmortizationInIncomeStatement":288850000.0,"DepreciationIncomeStatement":288850000.0,"GrossProfit":2801860000.0,"CostOfRevenue":4994830000.0,"TotalRevenue":7796690000.0,"OperatingRevenue":7796690000.0},"1751241600000":{"TaxEffectOfUnusualItems":0.0,"TaxRateForCalcs":0.200932,"NormalizedEBITDA":1523720000.0,"NetIncomeFromContinuingOperationNetMinorityInterest":1042240000.0,"ReconciledDepreciation":208030000.0,"ReconciledCostOfRevenue":4938790000.0,"EBITDA":1523720000.0,"EBIT":1315690000.0,"NetInterestIncome":-11370000.0,"InterestExpense":11370000.0,"NormalizedIncome":1042240000.0,"NetIncomeFromContinuingAndDiscontinuedOperation":1042240000.0,"TotalExpenses":6872840000.0,"DilutedAverageShares":75197691.0,"BasicAverageShares":75197691.0,"DilutedEPS":13.86,"BasicEPS":13.86,"DilutedNIAvailtoComStockholders":1042240000.0,"NetIncomeCommonStockholders":1042240000.0,"OtherunderPreferredStockDividend":0.0,"NetIncome":1042240000.0,"NetIncomeIncludingNoncontrollingInterests":1042240000.0,"NetIncomeContinuousOperations":1042240000.0,"TaxProvision":262080000.0,"PretaxIncome":1304320000.0,"OtherNonOperatingIncomeExpenses":100360000.0,"NetNonOperatingInterestIncomeExpense":-11370000.0,"InterestExpenseNonOperating":11370000.0,"OperatingIncome":1215330000.0,"OperatingExpense":1934050000.0,"OtherOperatingExpenses":1294030000.0,"DepreciationAndAmortizationInIncomeStatement":208030000.0,"DepreciationIncomeStatement":208030000.0,"GrossProfit":3149380000.0,"CostOfRevenue":4938790000.0,"TotalRevenue":8088170000.0,"OperatingRevenue":8088170000.0},"1743379200000":{"TaxEffectOfUnusualItems":0.0,"TaxRateForCalcs":0.072961,"NormalizedEBITDA":2235910000.0,"NetIncomeFromContinuingOperationNetMinorityInterest":1868270000.0,"ReconciledDepreciation":208680000.0,"ReconciledCostOfRevenue":7379410000.0,"EBITDA":2235910000.0,"EBIT":2027230000.0,"NetInterestIncome":208570000.0,"InterestExpense":11920000.0,"NormalizedIncome":1868270000.0,"NetIncomeFromContinuingAndDiscontinuedOperation":1868270000.0,"TotalExpenses":7335040000.0,"DilutedAverageShares":null,"BasicAverageShares":null,"DilutedEPS":null,"BasicEPS":null,"DilutedNIAvailtoComStockholders":1868270000.0,"NetIncomeCommonStockholders":1868270000.0,"OtherunderPreferredStockDividend":0.0,"NetIncome":1868270000.0,"NetIncomeIncludingNoncontrollingInterests":1868270000.0,"NetIncomeContinuousOperations":1868270000.0,"TaxProvision":147040000.0,"PretaxIncome":2015310000.0,"OtherNonOperatingIncomeExpenses":-311300000.0,"NetNonOperatingInterestIncomeExpense":208570000.0,"InterestExpenseNonOperating":11920000.0,"OperatingIncome":1926680000.0,"OperatingExpense":-44370000.0,"OtherOperatingExpenses":-1595090000.0,"DepreciationAndAmortizationInIncomeStatement":208680000.0,"DepreciationIncomeStatement":161640000.0,"GrossProfit":1882310000.0,"CostOfRevenue":7379410000.0,"TotalRevenue":9261720000.0,"OperatingRevenue":9261720000.0},"1735603200000":{"TaxEffectOfUnusualItems":0.0,"TaxRateForCalcs":0.240544,"NormalizedEBITDA":1252470000.0,"NetIncomeFromContinuingOperationNetMinorityInterest":782080000.0,"ReconciledDepreciation":211840000.0,"ReconciledCostOfRevenue":4145240000.0,"EBITDA":1252470000.0,"EBIT":1040630000.0,"NetInterestIncome":-10840000.0,"InterestExpense":10840000.0,"NormalizedIncome":782080000.0,"NetIncomeFromContinuingAndDiscontinuedOperation":782080000.0,"TotalExpenses":5937850000.0,"DilutedAverageShares":75200000.0,"BasicAverageShares":75200000.0,"DilutedEPS":10.4,"BasicEPS":10.4,"DilutedNIAvailtoComStockholders":782080000.0,"NetIncomeCommonStockholders":782080000.0,"OtherunderPreferredStockDividend":0.0,"NetIncome":782080000.0,"NetIncomeIncludingNoncontrollingInterests":782080000.0,"NetIncomeContinuousOperations":782080000.0,"TaxProvision":247710000.0,"PretaxIncome":1029790000.0,"OtherNonOperatingIncomeExpenses":144970000.0,"NetNonOperatingInterestIncomeExpense":-10840000.0,"InterestExpenseNonOperating":10840000.0,"OperatingIncome":895660000.0,"OperatingExpense":1792610000.0,"OtherOperatingExpenses":1143160000.0,"DepreciationAndAmortizationInIncomeStatement":211840000.0,"DepreciationIncomeStatement":211840000.0,"GrossProfit":2688270000.0,"CostOfRevenue":4145240000.0,"TotalRevenue":6833510000.0,"OperatingRevenue":6833510000.0},"1727654400000":{"TaxEffectOfUnusualItems":0.0,"TaxRateForCalcs":0.272536,"NormalizedEBITDA":1454890000.0,"NetIncomeFromContinuingOperationNetMinorityInterest":899480000.0,"ReconciledDepreciation":209020000.0,"ReconciledCostOfRevenue":4570000000.0,"EBITDA":1454890000.0,"EBIT":1245870000.0,"NetInterestIncome":-9410000.0,"InterestExpense":9410000.0,"NormalizedIncome":899480000.0,"NetIncomeFromContinuingAndDiscontinuedOperation":899480000.0,"TotalExpenses":6404360000.0,"DilutedAverageShares":75207358.0,"BasicAverageShares":75207358.0,"DilutedEPS":11.96,"BasicEPS":11.96,"DilutedNIAvailtoComStockholders":899480000.0,"NetIncomeCommonStockholders":899480000.0,"OtherunderPreferredStockDividend":0.0,"NetIncome":899480000.0,"NetIncomeIncludingNoncontrollingInterests":899480000.0,"NetIncomeContinuousOperations":899480000.0,"TaxProvision":336980000.0,"PretaxIncome":1236460000.0,"OtherNonOperatingIncomeExpenses":121370000.0,"NetNonOperatingInterestIncomeExpense":-9410000.0,"InterestExpenseNonOperating":9410000.0,"OperatingIncome":1124500000.0,"OperatingExpense":1834360000.0,"OtherOperatingExpenses":1203580000.0,"DepreciationAndAmortizationInIncomeStatement":209020000.0,"DepreciationIncomeStatement":209020000.0,"GrossProfit":2958860000.0,"CostOfRevenue":4570000000.0,"TotalRevenue":7528860000.0,"OperatingRevenue":7528860000.0}}